vision/client/__init__.py
vision/client/library/__init__.py
vision/client/library/api.py
vision/client/library/blockchains/__init__.py
vision/client/library/blockchains/avalanche.py
vision/client/library/blockchains/base.py
vision/client/library/blockchains/bnbchain.py
vision/client/library/blockchains/celo.py
vision/client/library/blockchains/cronos.py
vision/client/library/blockchains/ethereum.py
vision/client/library/blockchains/factory.py
vision/client/library/blockchains/polygon.py
vision/client/library/blockchains/solana.py
vision/client/library/blockchains/sonic.py
vision/client/library/business/__init__.py
vision/client/library/business/base.py
vision/client/library/business/bids.py
vision/client/library/business/deployments.py
vision/client/library/business/tokens.py
vision/client/library/business/transfers.py
vision/client/library/configuration.py
vision/client/library/constants.py
vision/client/library/entitites.py
vision/client/library/exceptions.py
vision/client/library/protocol.py
vision/client-library.env
vision/client-library.yml
vision_client_library-0.2.0.dist-info/LICENSE.md
vision_client_library-0.2.0.dist-info/WHEEL
vision_client_library-0.2.0.dist-info/RECORD
vision_client_library-0.2.0.dist-info/METADATA
