Metadata-Version: 2.1
Name: vision-client-library
Version: 0.2.0
Summary: Client library for engaging with the Vision system
License: GPL-3.0-only
Author: Vision XXX
Author-email: contact@notemail.com
Requires-Python: >=3.13,<4.0
Classifier: License :: OSI Approved :: GNU General Public License v3 (GPLv3)
Classifier: Programming Language :: Python :: 3
Classifier: Programming Language :: Python :: 3.13
Requires-Dist: vision-common (==0.3.1) ; python_version >= "3.13" and python_version < "4.0"
Requires-Dist: cerberus (==1.3.4) ; python_version >= "3.13" and python_version < "4.0"
Requires-Dist: pyyaml (==6.0.1) ; python_version >= "3.13" and python_version < "4.0"
Requires-Dist: requests (==2.32.3) ; python_version >= "3.13" and python_version < "4.0"
Requires-Dist: pyaml-env (==1.2.2) ; python_version >= "3.13" and python_version < "4.0"
Requires-Dist: python-dotenv (==1.0.1) ; python_version >= "3.13" and python_version < "4.0"
Requires-Dist: hexbytes (==1.2.1) ; python_version >= "3.13" and python_version < "4"
Requires-Dist: semantic-version (==2.10.0) ; python_version >= "3.13" and python_version < "4.0"
Requires-Dist: aiohappyeyeballs (==2.6.1) ; python_version >= "3.13" and python_version < "4"
Requires-Dist: aiohttp (==3.11.16) ; python_version >= "3.13" and python_version < "4"
Requires-Dist: aiosignal (==1.3.2) ; python_version >= "3.13" and python_version < "4"
Requires-Dist: amqp (==5.3.1) ; python_version >= "3.13" and python_version < "4.0"
Requires-Dist: aniso8601 (==10.0.0) ; python_version >= "3.13" and python_version < "4.0"
Requires-Dist: annotated-types (==0.7.0) ; python_version >= "3.13" and python_version < "4"
Requires-Dist: attrs (==25.3.0) ; python_version >= "3.13" and python_version < "4"
Requires-Dist: billiard (==4.2.1) ; python_version >= "3.13" and python_version < "4.0"
Requires-Dist: bitarray (==3.3.0) ; python_version >= "3.13" and python_version < "4"
Requires-Dist: blinker (==1.9.0) ; python_version >= "3.13" and python_version < "4.0"
Requires-Dist: cached-property (==2.0.1) ; python_version >= "3.13" and python_version < "4"
Requires-Dist: celery (==5.3.1) ; python_version >= "3.13" and python_version < "4.0"
Requires-Dist: certifi (==2025.1.31) ; python_version >= "3.13" and python_version < "4.0"
Requires-Dist: charset-normalizer (==3.4.1) ; python_version >= "3.13" and python_version < "4.0"
Requires-Dist: ckzg (==2.1.1) ; python_version >= "3.13" and python_version < "4"
Requires-Dist: click (==8.1.8) ; python_version >= "3.13" and python_version < "4.0"
Requires-Dist: click-didyoumean (==0.3.1) ; python_version >= "3.13" and python_version < "4.0"
Requires-Dist: click-plugins (==1.1.1) ; python_version >= "3.13" and python_version < "4.0"
Requires-Dist: click-repl (==0.3.0) ; python_version >= "3.13" and python_version < "4.0"
Requires-Dist: colorama (==0.4.6) ; python_version >= "3.13" and python_version < "4.0" and platform_system == "Windows"
Requires-Dist: cytoolz (==1.0.1) ; python_version >= "3.13" and python_version < "4" and implementation_name == "cpython"
Requires-Dist: eth-abi (==5.2.0) ; python_version >= "3.13" and python_version < "4"
Requires-Dist: eth-account (==0.13.1) ; python_version >= "3.13" and python_version < "4"
Requires-Dist: eth-hash (==0.7.1) ; python_version >= "3.13" and python_version < "4"
Requires-Dist: eth-keyfile (==0.9.1) ; python_version >= "3.13" and python_version < "4"
Requires-Dist: eth-keys (==0.6.1) ; python_version >= "3.13" and python_version < "4"
Requires-Dist: eth-rlp (==2.2.0) ; python_version >= "3.13" and python_version < "4"
Requires-Dist: eth-typing (==5.2.0) ; python_version >= "3.13" and python_version < "4"
Requires-Dist: eth-utils (==5.2.0) ; python_version >= "3.13" and python_version < "4"
Requires-Dist: flask (==3.1.0) ; python_version >= "3.13" and python_version < "4.0"
Requires-Dist: flask-restful (==0.3.10) ; python_version >= "3.13" and python_version < "4.0"
Requires-Dist: frozenlist (==1.5.0) ; python_version >= "3.13" and python_version < "4"
Requires-Dist: idna (==3.10) ; python_version >= "3.13" and python_version < "4.0"
Requires-Dist: itsdangerous (==2.2.0) ; python_version >= "3.13" and python_version < "4.0"
Requires-Dist: jinja2 (==3.1.6) ; python_version >= "3.13" and python_version < "4.0"
Requires-Dist: json-log-formatter (==0.5.2) ; python_version >= "3.13" and python_version < "4.0"
Requires-Dist: kombu (==5.5.2) ; python_version >= "3.13" and python_version < "4.0"
Requires-Dist: markupsafe (==3.0.2) ; python_version >= "3.13" and python_version < "4.0"
Requires-Dist: marshmallow (==3.26.1) ; python_version >= "3.13" and python_version < "4.0"
Requires-Dist: multidict (==6.3.2) ; python_version >= "3.13" and python_version < "4"
Requires-Dist: packaging (==24.2) ; python_version >= "3.13" and python_version < "4.0"
Requires-Dist: parsimonious (==0.10.0) ; python_version >= "3.13" and python_version < "4"
Requires-Dist: prompt-toolkit (==3.0.50) ; python_version >= "3.13" and python_version < "4.0"
Requires-Dist: propcache (==0.3.1) ; python_version >= "3.13" and python_version < "4"
Requires-Dist: py-ecc (==7.0.1) ; python_version >= "3.13" and python_version < "4"
Requires-Dist: pycryptodome (==3.20.0) ; python_version >= "3.13" and python_version < "4.0"
Requires-Dist: pydantic (==2.11.2) ; python_version >= "3.13" and python_version < "4"
Requires-Dist: pydantic-core (==2.33.1) ; python_version >= "3.13" and python_version < "4"
Requires-Dist: python-dateutil (==2.9.0.post0) ; python_version >= "3.13" and python_version < "4.0"
Requires-Dist: pytz (==2025.2) ; python_version >= "3.13" and python_version < "4.0"
Requires-Dist: pyunormalize (==16.0.0) ; python_version >= "3.13" and python_version < "4"
Requires-Dist: pywin32 (==310) ; python_version >= "3.13" and python_version < "4" and platform_system == "Windows"
Requires-Dist: regex (==2024.11.6) ; python_version >= "3.13" and python_version < "4"
Requires-Dist: rlp (==4.1.0) ; python_version >= "3.13" and python_version < "4"
Requires-Dist: setuptools (==78.1.0) ; python_version >= "3.13" and python_version < "4.0"
Requires-Dist: six (==1.17.0) ; python_version >= "3.13" and python_version < "4.0"
Requires-Dist: toolz (==1.0.0) ; python_version >= "3.13" and python_version < "4" and (implementation_name == "pypy" or implementation_name == "cpython")
Requires-Dist: types-requests (==2.32.0.20250328) ; python_version >= "3.13" and python_version < "4"
Requires-Dist: typing-extensions (==4.13.1) ; python_version >= "3.13" and python_version < "4"
Requires-Dist: typing-inspection (==0.4.0) ; python_version >= "3.13" and python_version < "4"
Requires-Dist: tzdata (==2025.2) ; python_version >= "3.13" and python_version < "4.0"
Requires-Dist: urllib3 (==2.3.0) ; python_version >= "3.13" and python_version < "4.0"
Requires-Dist: vine (==5.1.0) ; python_version >= "3.13" and python_version < "4.0"
Requires-Dist: wcwidth (==0.2.13) ; python_version >= "3.13" and python_version < "4.0"
Requires-Dist: web3 (==7.10.0) ; python_version >= "3.13" and python_version < "4"
Requires-Dist: websockets (==15.0.1) ; python_version >= "3.13" and python_version < "4"
Requires-Dist: werkzeug (==3.1.3) ; python_version >= "3.13" and python_version < "4.0"
Requires-Dist: yarl (==1.18.3) ; python_version >= "3.13" and python_version < "4"
Requires-Dist: eth-hash (==0.7.1) ; python_version >= "3.13" and python_version < "4"
